catbackupAPI/CatbackupAPI_NPP.py
catbackupAPI/__init__.py
catbackupAPI/__main__.py
CatbackupAPI_NPP-1.6.1.dist-info/METADATA
CatbackupAPI_NPP-1.6.1.dist-info/WHEEL
CatbackupAPI_NPP-1.6.1.dist-info/entry_points.txt
CatbackupAPI_NPP-1.6.1.dist-info/top_level.txt
CatbackupAPI_NPP-1.6.1.dist-info/RECORD
