Metadata-Version: 2.1
Name: CatbackupAPI-NPP
Version: 1.6.1
Summary: Programa per recoleccio de dades d'apis de CatBackup
Home-page: https://github.com/NilPujolPorta/CatbackupAPI-NPP
Author: Nil Pujol Porta
Author-email: nilpujolporta@gmail.com
License: GNU
Platform: UNKNOWN
Requires-Dist: argparse
Requires-Dist: setuptools (>=42)
Requires-Dist: wheel
Requires-Dist: openpyxl
Requires-Dist: pyyaml
Requires-Dist: requests
Requires-Dist: mysql-connector-python
Requires-Dist: tqdm
Requires-Dist: opencv-python
Requires-Dist: pyotp
Requires-Dist: pytesseract
Requires-Dist: selenium
Requires-Dist: wget
